{"data":[{"numeral":"0","cardinal":"zêro"},{"numeral":"1","cardinal":"un"},{"numeral":"2","cardinal":"doìdoe"},{"numeral":"3","cardinal":"treitræ"},{"numeral":"4","cardinal":"quattro"},{"numeral":"5","cardinal":"çinque"},{"numeral":"6","cardinal":"sei"},{"numeral":"7","cardinal":"sette"},{"numeral":"8","cardinal":"eutto"},{"numeral":"9","cardinal":"neuve"},{"numeral":"10","cardinal":"dexe"},{"numeral":"11","cardinal":"onze"},{"numeral":"12","cardinal":"dozze"},{"numeral":"13","cardinal":"trezze"},{"numeral":"14","cardinal":"quattòrze"},{"numeral":"15","cardinal":"chinze"},{"numeral":"16","cardinal":"sezze"},{"numeral":"17","cardinal":"dïsette"},{"numeral":"18","cardinal":"dixeutto"},{"numeral":"19","cardinal":"dixineuve"},{"numeral":"20","cardinal":"vinti"},{"numeral":"21","cardinal":"vintiun"},{"numeral":"22","cardinal":"vintidoìvintidoe"},{"numeral":"23","cardinal":"vintitrei"},{"numeral":"24","cardinal":"vintiquattro"},{"numeral":"25","cardinal":"vintiçinque"},{"numeral":"26","cardinal":"vintisei"},{"numeral":"27","cardinal":"vintisette"},{"numeral":"28","cardinal":"vinteutto"},{"numeral":"29","cardinal":"vintineuve"},{"numeral":"30","cardinal":"trenta"},{"numeral":"40","cardinal":"quaranta"},{"numeral":"50","cardinal":"çinquanta"},{"numeral":"60","cardinal":"sciuscianta"},{"numeral":"70","cardinal":"settanta"},{"numeral":"80","cardinal":"ottanta"},{"numeral":"90","cardinal":"novanta"},{"numeral":"100","cardinal":"çento"},{"numeral":"200","cardinal":"duxento"},{"numeral":"300","cardinal":"trexento"},{"numeral":"400","cardinal":"quattroçento"},{"numeral":"500","cardinal":"çinqueçento"},{"numeral":"600","cardinal":"seiçento"},{"numeral":"700","cardinal":"setteçento"},{"numeral":"800","cardinal":"euttoçento"},{"numeral":"900","cardinal":"neuveçento"},{"numeral":"1000","cardinal":"mille"},{"numeral":"2000","cardinal":"doamïa"},{"numeral":"1","cardinal":"un"},{"numeral":"1","cardinal":"un"}]}