{"data":[{"numeral":"1","cardinalnumbers":"э̄ххт"},{"numeral":"2","cardinalnumbers":"кӯhт"},{"numeral":"3","cardinalnumbers":"кōллм"},{"numeral":"4","cardinalnumbers":"нēлльй"},{"numeral":"5","cardinalnumbers":"выдт"},{"numeral":"6","cardinalnumbers":"кудт"},{"numeral":"7","cardinalnumbers":"кыджемь"},{"numeral":"8","cardinalnumbers":"кāххц"},{"numeral":"9","cardinalnumbers":"аххц"},{"numeral":"10","cardinalnumbers":"лоагкь"},{"numeral":"11","cardinalnumbers":"э̄ххтэмплоакгь"},{"numeral":"12","cardinalnumbers":"кӯhтэмплоагкь"},{"numeral":"13","cardinalnumbers":"кōллмэмплоакгь"},{"numeral":"14","cardinalnumbers":"нēлльйэмплоакгь"},{"numeral":"15","cardinalnumbers":"выдтэмплоакгь"},{"numeral":"16","cardinalnumbers":"кудтэмплоакгь"},{"numeral":"17","cardinalnumbers":"кыджемьэмплоакгь"},{"numeral":"18","cardinalnumbers":"кāххцэмплоакгь"},{"numeral":"19","cardinalnumbers":"аххцэмплоакгь"},{"numeral":"20","cardinalnumbers":"кӯhтлоагкь"},{"numeral":"21","cardinalnumbers":"кӯhтлоагкьэ̄ххт"},{"numeral":"22","cardinalnumbers":"кӯhтлоагкькӯhт"},{"numeral":"23","cardinalnumbers":"кӯhтлоагкькōллм"},{"numeral":"24","cardinalnumbers":"кӯhтлоагкьнēлльй"},{"numeral":"25","cardinalnumbers":"кӯhтлоагкьвыдт"},{"numeral":"26","cardinalnumbers":"кӯhтлоагкькудт"},{"numeral":"27","cardinalnumbers":"кӯhтлоагкькыджемь"},{"numeral":"28","cardinalnumbers":"кӯhтлоагкькāххц"},{"numeral":"29","cardinalnumbers":"кӯhтлоагкьаххц"},{"numeral":"30","cardinalnumbers":"кōллмлоагкь"},{"numeral":"40","cardinalnumbers":"нēлльйлоагкь"},{"numeral":"50","cardinalnumbers":"выдтлоагкь"},{"numeral":"60","cardinalnumbers":"кудтлоагкь"},{"numeral":"70","cardinalnumbers":"кыджемьлоагкь"},{"numeral":"80","cardinalnumbers":"кāххцлоагкь"},{"numeral":"90","cardinalnumbers":"аххцлоагкь"},{"numeral":"100","cardinalnumbers":"чӯдтҍ"},{"numeral":"200","cardinalnumbers":"кӯxxтчӯдтҍ"},{"numeral":"1000","cardinalnumbers":"тоафант"},{"numeral":"2000","cardinalnumbers":"кӯxxттоафант"}]}