{"data":[{"numeral":"1","cardinal":"ësa","ordinal":"puru’meru"},{"numeral":"2","cardinal":"éduwa","ordinal":"ikaduwa"},{"numeral":"3","cardinal":"étélo","ordinal":"ikatélo"},{"numeral":"4","cardinal":"épat","ordinal":"ikaépat"},{"numeral":"5","cardinal":"lima","ordinal":"ikalima"},{"numeral":"6","cardinal":"éném","ordinal":"ikaéném"},{"numeral":"7","cardinal":"pitu","ordinal":"ikapitu"},{"numeral":"8","cardinal":"walu","ordinal":"ikawalu"},{"numeral":"9","cardinal":"siyam","ordinal":"ikasiyam"},{"numeral":"10","cardinal":"‘sapulu","ordinal":"ikasapulu"},{"numeral":"11","cardinal":"‘sapulu","ordinal":""},{"numeral":"12","cardinal":"‘sapulu","ordinal":""},{"numeral":"13","cardinal":"‘sapulu","ordinal":""},{"numeral":"14","cardinal":"‘sapulu","ordinal":""},{"numeral":"15","cardinal":"‘sapulu","ordinal":""},{"numeral":"16","cardinal":"‘sapulu","ordinal":""},{"numeral":"17","cardinal":"‘sapulu","ordinal":""},{"numeral":"18","cardinal":"‘sapulu","ordinal":""},{"numeral":"19","cardinal":"‘sapulu","ordinal":""},{"numeral":"20","cardinal":"du’wapulu","ordinal":""},{"numeral":"21","cardinal":"du’wapulu","ordinal":""},{"numeral":"22","cardinal":"du’wapulu","ordinal":""},{"numeral":"23","cardinal":"du’wapulu","ordinal":""},{"numeral":"24","cardinal":"du’wapulu","ordinal":""},{"numeral":"25","cardinal":"du’wapulu","ordinal":""},{"numeral":"26","cardinal":"du’wapulu","ordinal":""},{"numeral":"27","cardinal":"du’wapulu","ordinal":""},{"numeral":"28","cardinal":"du’wapulu","ordinal":""},{"numeral":"29","cardinal":"du’wapulu","ordinal":""},{"numeral":"30","cardinal":"étélo","ordinal":""},{"numeral":"40","cardinal":"épat","ordinal":""},{"numeral":"50","cardinal":"l’ima","ordinal":""},{"numeral":"60","cardinal":"éném","ordinal":""},{"numeral":"70","cardinal":"pitu","ordinal":""},{"numeral":"80","cardinal":"walu","ordinal":""},{"numeral":"90","cardinal":"siyam","ordinal":""},{"numeral":"100","cardinal":"sandaan","ordinal":""},{"numeral":"200","cardinal":"éduwa","ordinal":""},{"numeral":"300","cardinal":"étélo","ordinal":""},{"numeral":"400","cardinal":"épat","ordinal":""},{"numeral":"500","cardinal":"lima","ordinal":""},{"numeral":"600","cardinal":"éném","ordinal":""},{"numeral":"700","cardinal":"pitu","ordinal":""},{"numeral":"800","cardinal":"walu","ordinal":""},{"numeral":"900","cardinal":"siyam","ordinal":""},{"numeral":"1000","cardinal":"libu","ordinal":""},{"numeral":"2000","cardinal":"éduwa","ordinal":""},{"numeral":"3000","cardinal":"étélo","ordinal":""},{"numeral":"4000","cardinal":"épat","ordinal":""},{"numeral":"5000","cardinal":"lima","ordinal":""},{"numeral":"6000","cardinal":"éném","ordinal":""},{"numeral":"7000","cardinal":"pitu","ordinal":""},{"numeral":"8000","cardinal":"walu","ordinal":""},{"numeral":"9000","cardinal":"siyam","ordinal":""},{"numeral":"10000","cardinal":"sapulu","ordinal":""},{"numeral":"once","cardinal":"ësa","ordinal":""},{"numeral":"twice","cardinal":"penduwa","ordinal":""},{"numeral":"three","cardinal":"pentélo","ordinal":""},{"numeral":"four","cardinal":"penépat","ordinal":""},{"numeral":"five","cardinal":"penlima","ordinal":""},{"numeral":"six","cardinal":"penéném","ordinal":""}]}