{"data":[{"numeral":"0","cardinalnumbers":"۰","ordinalnumbers":"","undefined":""},{"numeral":"1","cardinalnumbers":"۱","ordinalnumbers":"","undefined":""},{"numeral":"2","cardinalnumbers":"۲","ordinalnumbers":"","undefined":""},{"numeral":"3","cardinalnumbers":"۳","ordinalnumbers":"","undefined":""},{"numeral":"4","cardinalnumbers":"۴","ordinalnumbers":"","undefined":""},{"numeral":"5","cardinalnumbers":"۵","ordinalnumbers":"","undefined":""},{"numeral":"6","cardinalnumbers":"۶","ordinalnumbers":"","undefined":""},{"numeral":"7","cardinalnumbers":"۷","ordinalnumbers":"","undefined":""},{"numeral":"8","cardinalnumbers":"۸","ordinalnumbers":"","undefined":""},{"numeral":"9","cardinalnumbers":"۹","ordinalnumbers":"","undefined":""},{"numeral":"10","cardinalnumbers":"۱۰","ordinalnumbers":"","undefined":""},{"numeral":"11","cardinalnumbers":"۱۱","ordinalnumbers":"","undefined":""},{"numeral":"12","cardinalnumbers":"۱۲","ordinalnumbers":"","undefined":""},{"numeral":"13","cardinalnumbers":"۱۳","ordinalnumbers":"","undefined":""},{"numeral":"14","cardinalnumbers":"۱۴","ordinalnumbers":"","undefined":""},{"numeral":"15","cardinalnumbers":"۱۵","ordinalnumbers":"","undefined":""},{"numeral":"16","cardinalnumbers":"۱۶","ordinalnumbers":"","undefined":""},{"numeral":"17","cardinalnumbers":"۱۷","ordinalnumbers":"","undefined":""},{"numeral":"18","cardinalnumbers":"۱۸","ordinalnumbers":"","undefined":""},{"numeral":"19","cardinalnumbers":"۱۹","ordinalnumbers":"","undefined":""},{"numeral":"20","cardinalnumbers":"۲۰","ordinalnumbers":"","undefined":""},{"numeral":"21","cardinalnumbers":"۲۱","ordinalnumbers":"","undefined":""},{"numeral":"22","cardinalnumbers":"۲۲","ordinalnumbers":"","undefined":""},{"numeral":"23","cardinalnumbers":"۲۳","ordinalnumbers":"","undefined":""},{"numeral":"24","cardinalnumbers":"۲۴","ordinalnumbers":"","undefined":""},{"numeral":"25","cardinalnumbers":"۲۵","ordinalnumbers":"","undefined":""},{"numeral":"26","cardinalnumbers":"۲۶","ordinalnumbers":"","undefined":""},{"numeral":"27","cardinalnumbers":"۲۷","ordinalnumbers":"","undefined":""},{"numeral":"28","cardinalnumbers":"۲۸","ordinalnumbers":"","undefined":""},{"numeral":"29","cardinalnumbers":"۲۹","ordinalnumbers":"","undefined":""},{"numeral":"30","cardinalnumbers":"۳۰","ordinalnumbers":"","undefined":""},{"numeral":"40","cardinalnumbers":"۴۰","ordinalnumbers":"","undefined":""},{"numeral":"50","cardinalnumbers":"۵۰","ordinalnumbers":"","undefined":""},{"numeral":"60","cardinalnumbers":"۶۰","ordinalnumbers":"","undefined":""},{"numeral":"70","cardinalnumbers":"۷۰","ordinalnumbers":"","undefined":""},{"numeral":"80","cardinalnumbers":"۸۰","ordinalnumbers":"","undefined":""},{"numeral":"90","cardinalnumbers":"۹۰","ordinalnumbers":"","undefined":""},{"numeral":"100","cardinalnumbers":"۱۰۰","ordinalnumbers":"","undefined":""},{"numeral":"1000","cardinalnumbers":"۱۰۰۰","ordinalnumbers":"","undefined":""},{"numeral":"1","cardinalnumbers":"۱۰۰۰۰۰۰","ordinalnumbers":"","undefined":""}]}